bottle_sqlite.py
bottle_sqlite-0.2.0.dist-info/LICENSE
bottle_sqlite-0.2.0.dist-info/METADATA
bottle_sqlite-0.2.0.dist-info/WHEEL
bottle_sqlite-0.2.0.dist-info/top_level.txt
bottle_sqlite-0.2.0.dist-info/RECORD
