Metadata-Version: 2.1
Name: bottle-sqlite
Version: 0.2.0
Summary: SQLite3 integration for Bottle.
Home-page: https://github.com/bottlepy/bottle-sqlite
Author: Marcel Hellkamp
Author-email: marc@gsites.de
License: MIT
Platform: any
Classifier: Environment :: Web Environment
Classifier: Intended Audience :: Developers
Classifier: License :: OSI Approved :: MIT License
Classifier: Operating System :: OS Independent
Classifier: Programming Language :: Python
Classifier: Topic :: Internet :: WWW/HTTP :: Dynamic Content
Classifier: Topic :: Software Development :: Libraries :: Python Modules
Requires: bottle (>=0.12)
